{
    "backend": "api-server-nodejs",
    "db_name": "",
    "db_pass": "",
    "db_type": "sqlite",
    "db_user": "",
    "dbms": "1",
    "description": "generated product",
    "design": "horizon-ui",
    "docker": "0",
    "err_code": 0,
    "frontend": "react",
    "heroku": "0",
    "pattern": "fullstack",
    "pro": "0",
    "task_id": "7ea54fa3-10d1-4ae1-812a-aaaed6ba0970",
    "task_info": "Upload Sources [0%] - 185 files",
    "task_output": "7ea54fa3-10d1-4ae1-812a-aaaed6ba0970.zip",
    "task_result": "SUCCESS",
    "task_state": "RUNNING",
    "task_ts_end": "2023-10-20-04-10-48",
    "task_ts_start": "2023-10-20-04-10-46"
}